{
  "name": "signatures",
  "rules": {
    "function_definition": {
      "type": "SEQ",
      "members": [
        {
          "type": "SYMBOL",
          "name": "function_name"
        },
        {
          "type": "STRING",
          "value": "("
        },
        {
          "type": "CHOICE",
          "members": [
            {
              "type": "SYMBOL",
              "name": "parameters"
            },
            {
              "type": "BLANK"
            }
          ]
        },
        {
          "type": "STRING",
          "value": ")"
        }
      ]
    },
    "parameters": {
      "type": "SEQ",
      "members": [
        {
          "type": "SYMBOL",
          "name": "parameter"
        },
        {
          "type": "REPEAT",
          "content": {
            "type": "SEQ",
            "members": [
              {
                "type": "STRING",
                "value": ","
              },
              {
                "type": "SYMBOL",
                "name": "parameter"
              }
            ]
          }
        }
      ]
    },
    "parameter": {
      "type": "SEQ",
      "members": [
        {
          "type": "CHOICE",
          "members": [
            {
              "type": "SYMBOL",
              "name": "primitive_type"
            },
            {
              "type": "SYMBOL",
              "name": "tuple_type"
            }
          ]
        },
        {
          "type": "SYMBOL",
          "name": "identifier"
        }
      ]
    },
    "tuple_type": {
      "type": "SEQ",
      "members": [
        {
          "type": "STRING",
          "value": "("
        },
        {
          "type": "CHOICE",
          "members": [
            {
              "type": "SYMBOL",
              "name": "types"
            },
            {
              "type": "BLANK"
            }
          ]
        },
        {
          "type": "STRING",
          "value": ")"
        }
      ]
    },
    "types": {
      "type": "SEQ",
      "members": [
        {
          "type": "SYMBOL",
          "name": "type"
        },
        {
          "type": "REPEAT",
          "content": {
            "type": "SEQ",
            "members": [
              {
                "type": "STRING",
                "value": ","
              },
              {
                "type": "SYMBOL",
                "name": "type"
              }
            ]
          }
        }
      ]
    },
    "type": {
      "type": "CHOICE",
      "members": [
        {
          "type": "SYMBOL",
          "name": "primitive_type"
        },
        {
          "type": "SYMBOL",
          "name": "tuple_type"
        }
      ]
    },
    "primitive_type": {
      "type": "PATTERN",
      "value": "[a-zA-Z_]\\w*"
    },
    "function_name": {
      "type": "PATTERN",
      "value": "[a-zA-Z_]\\w*"
    },
    "identifier": {
      "type": "PATTERN",
      "value": "[a-zA-Z_]\\w*"
    }
  },
  "extras": [
    {
      "type": "PATTERN",
      "value": "\\s"
    }
  ],
  "conflicts": [],
  "precedences": [],
  "externals": [],
  "inline": [],
  "supertypes": []
}
